HW3/PRJ/HW3.v
`timescale 1ns / 1ns

module traffic_light (
    output HGS, HGL, HGR, HY, HR, FG, FY, FR,
    input clk, reset    
    );
    
    wire [1:0] ST_connect, T_connect;
    
    controller Controller (
        .HGS(HGS),
        .HGL(HGL), 
        .HGR(HGR), 
        .HY(HY), 
        .HR(HR), 
        .FG(FG), 
        .FY(FY), 
        .FR(FR), 
        .ST_out(ST_connect), 
        .Trigger(T_connect),  
        .clk(clk), 
        .reset(reset)
        );
                                                                                                    
    counter Counter (
        .Trigger_out(T_connect),
        .clk(clk),
        .reset(reset),
        .ST(ST_connect)
        );
endmodule

module controller (
    output HGS, HGL, HGR, HY, HR, FG, FY, FR, 
    output reg[1:0] ST_out,
    input [1:0]Trigger,
    input clk, reset
    );
    
    reg[1:0] ST; // state & nxt state 
    reg[2:0] state, nxt_state;
    
    parameter S0 = 3'b000, S1 = 3'b001, S2 = 3'b010, S3 = 3'b011, S4 = 3'b100, S5 = 3'b101;
    parameter TL = 2'b11, TN = 2'b10, TS = 2'b01;
    assign HGS = (state == S0);
    assign HGL = (state == S4);
    assign HGR = (state == S0);
    assign HY = (state == S1) || (state == S5);
    assign HR = (state == S2) || (state == S3) || (state == S4) || (state == S5);
    assign FG = (state == S2);
    assign FY = (state == S3);
    assign FR = (state == S0) || (state == S1) || (state == S4) || (state == S5);
    
    // flip-flops
    always @ (posedge clk or posedge reset)
        if (reset) // an asynchronuous reset                                                                                           
        begin
            state <= S0;
            ST_out <= 2'b00;
        end
        else begin
            state <= nxt_state;
            ST_out <= ST;
        end
    
    // Combinational circuit
    always @ (state or Trigger)                                                                                             
        case (state) // state transition
            S0: if (Trigger == TL) begin
                    nxt_state = S1;
                    ST = TS;
                end
                else begin
                    nxt_state = S0;
                    ST = 2'b00;
                end
            S1: if (Trigger == TS) begin
                    nxt_state = S4;
                    ST = TN;
                end
                else begin
                    nxt_state = S1;
                    ST = 2'b00;
                end
            S2: if (Trigger == TL) begin
                    nxt_state = S3;
                    ST = TS;
                end
                else begin
                    nxt_state = S2;
                    ST = 2'b00;
                end
            S3: if (Trigger == TS) begin
                    nxt_state = S0;
                    ST = TL;
                end
                else begin
                    nxt_state = S3;
                    ST = 2'b00;
                end
            S4: if (Trigger == TN) begin
                    nxt_state = S5;
                    ST = TS;
                end
                else begin
                    nxt_state = S4;
                    ST = 2'b00;
                end
            S5: if (Trigger == TS) begin
                    nxt_state = S2;
                    ST = TL;
                end
                else begin
                    nxt_state = S5;
                    ST = 2'b00;
                end
        endcase
        
endmodule

module counter (
    output reg [1:0]Trigger_out,
    input clk, reset,
    input [1:0] ST 
    );
    
    reg [5:0]count;
    reg [1:0]state;
    
    parameter L = 7, N = 5, S = 3;
    parameter TL = 2'b11, TN = 2'b10, TS = 2'b01;
    
    always @ (posedge clk) begin
        if (reset) begin
            count <= L;
            Trigger_out <= 2'b00; 
            state <= TL;
        end       
        else begin
            if (ST == 2'b00 && count != 0) begin
                count <= count - 1;
            end
            else begin
                state <= ST;
                case (ST)
                    TL: count <= L;
                    TN: count <= N;
                    TS: count <= S;
                endcase
            end
            
            if (count == 0) begin
                Trigger_out <= state;
            end
        end
    end
    
    
endmodule

HW3/PRJ/tb_HW3.v
`timescale 1ns / 1ns
`include "HW3.v"

module tb_HW3;
    
    //Inputs
    reg clk, reset;
    //Outputs
    wire HGS, HGL, HGR, HY, HR, FG, FY, FR;
    
    traffic_light TL (
        .HGS(HGS),
        .HGL(HGL), 
        .HGR(HGR), 
        .HY(HY), 
        .HR(HR), 
        .FG(FG), 
        .FY(FY), 
        .FR(FR), 
        .clk(clk), 
        .reset(reset)
        );
                                                                                                    
    
    initial begin
        clk = 1'b0;
        reset = 1'b0;
    end
    
    always begin
        #10 clk = ~clk;
    end
        
    initial begin
        #20 reset = 1'b1;
        #40 reset = 1'b0;
        #1200 $finish;
    end
    
    initial begin
        $dumpfile("HW3.vcd");
        $dumpvars;
    end
    
endmodule

HW3/PRJ/HW3.vcd
$date
    May 27, 2018  18:17:35
$end
$version
    TOOL:	ncsim	14.10-s005
$end
$timescale
    1 ns
$end

$scope module tb_HW3 $end
$var reg       1 !    clk  $end
$var reg       1 "    reset  $end
$var wire      1 #    HGS  $end
$var wire      1 $    HGL  $end
$var wire      1 #    HGR  $end
$var wire      1 %    HY  $end
$var wire      1 &    HR  $end
$var wire      1 '    FG  $end
$var wire      1 (    FY  $end
$var wire      1 )    FR  $end

$scope module TL $end
$var wire      1 #    HGS  $end
$var wire      1 $    HGL  $end
$var wire      1 #    HGR  $end
$var wire      1 %    HY  $end
$var wire      1 &    HR  $end
$var wire      1 '    FG  $end
$var wire      1 (    FY  $end
$var wire      1 )    FR  $end
$var wire      1 *    clk  $end
$var wire      1 +    reset  $end
$var wire      2 ,    ST_connect [1:0] $end
$var wire      2 -    T_connect [1:0] $end

$scope module Controller $end
$var wire      1 #    HGS  $end
$var wire      1 $    HGL  $end
$var wire      1 #    HGR  $end
$var wire      1 %    HY  $end
$var wire      1 &    HR  $end
$var wire      1 '    FG  $end
$var wire      1 (    FY  $end
$var wire      1 )    FR  $end
$var reg       2 .    ST_out [1:0] $end
$var wire      2 -    Trigger [1:0] $end
$var wire      1 *    clk  $end
$var wire      1 +    reset  $end
$var reg       2 /    ST [1:0] $end
$var reg       3 0    state [2:0] $end
$var reg       3 1    nxt_state [2:0] $end
$var parameter  3 2    S0  $end
$var parameter  3 3    S1  $end
$var parameter  3 4    S2  $end
$var parameter  3 5    S3  $end
$var parameter  3 6    S4  $end
$var parameter  3 7    S5  $end
$var parameter  2 8    TL  $end
$var parameter  2 9    TN  $end
$var parameter  2 :    TS  $end
$upscope $end


$scope module Counter $end
$var reg       2 ;    Trigger_out [1:0] $end
$var wire      1 *    clk  $end
$var wire      1 +    reset  $end
$var wire      2 ,    ST [1:0] $end
$var reg       6 <    count [5:0] $end
$var reg       2 =    state [1:0] $end
$var parameter 32 >    L  $end
$var parameter 32 ?    N  $end
$var parameter 32 @    S  $end
$var parameter  2 A    TL  $end
$var parameter  2 B    TN  $end
$var parameter  2 C    TS  $end
$upscope $end

$upscope $end

$upscope $end

$enddefinitions $end
$dumpvars
b1 C
b10 B
b11 A
b11 @
b101 ?
b111 >
b1 :
b10 9
b11 8
b101 7
b100 6
b11 5
b10 4
b1 3
b0 2
0!
0"
x#
x$
x%
x&
x'
x(
x)
0*
0+
bx ,
bx -
bx .
bx /
bx 0
bx 1
bx ;
bx <
bx =
$end
#10
1!
1*
#20
1"
0!
0*
1+
b0 0
b0 .
b0 1
b0 /
1)
0(
0'
0&
0%
1#
0$
b0 ,
#30
1!
1*
b111 <
b0 ;
b11 =
b0 -
#40
0!
0*
#50
1!
1*
#60
0"
0!
0*
0+
#70
1!
1*
b110 <
#80
0!
0*
#90
1!
1*
b101 <
#100
0!
0*
#110
1!
1*
b100 <
#120
0!
0*
#130
1!
1*
b11 <
#140
0!
0*
#150
1!
1*
b10 <
#160
0!
0*
#170
1!
1*
b1 <
#180
0!
0*
#190
1!
1*
b0 <
#200
0!
0*
#210
1!
1*
b0 =
b11 ;
b11 -
b1 1
b1 /
#220
0!
0*
#230
1!
1*
b1 0
b1 .
b0 ;
b0 /
1%
0#
b0 -
b1 ,
#240
0!
0*
#250
1!
1*
b0 .
b1 =
b11 <
b0 ,
#260
0!
0*
#270
1!
1*
b10 <
#280
0!
0*
#290
1!
1*
b1 <
#300
0!
0*
#310
1!
1*
b0 <
#320
0!
0*
#330
1!
1*
b0 =
b1 ;
b1 -
b100 1
b10 /
#340
0!
0*
#350
1!
1*
b100 0
b10 .
b0 ;
b0 /
1&
0%
1$
b0 -
b10 ,
#360
0!
0*
#370
1!
1*
b0 .
b10 =
b101 <
b0 ,
#380
0!
0*
#390
1!
1*
b100 <
#400
0!
0*
#410
1!
1*
b11 <
#420
0!
0*
#430
1!
1*
b10 <
#440
0!
0*
#450
1!
1*
b1 <
#460
0!
0*
#470
1!
1*
b0 <
#480
0!
0*
#490
1!
1*
b0 =
b10 ;
b10 -
b101 1
b1 /
#500
0!
0*
#510
1!
1*
b101 0
b1 .
b0 ;
b0 /
1%
0$
b0 -
b1 ,
#520
0!
0*
#530
1!
1*
b0 .
b1 =
b11 <
b0 ,
#540
0!
0*
#550
1!
1*
b10 <
#560
0!
0*
#570
1!
1*
b1 <
#580
0!
0*
#590
1!
1*
b0 <
#600
0!
0*
#610
1!
1*
b0 =
b1 ;
b1 -
b10 1
b11 /
#620
0!
0*
#630
1!
1*
b10 0
b11 .
b0 ;
b0 /
0)
1'
0%
b0 -
b11 ,
#640
0!
0*
#650
1!
1*
b0 .
b11 =
b111 <
b0 ,
#660
0!
0*
#670
1!
1*
b110 <
#680
0!
0*
#690
1!
1*
b101 <
#700
0!
0*
#710
1!
1*
b100 <
#720
0!
0*
#730
1!
1*
b11 <
#740
0!
0*
#750
1!
1*
b10 <
#760
0!
0*
#770
1!
1*
b1 <
#780
0!
0*
#790
1!
1*
b0 <
#800
0!
0*
#810
1!
1*
b0 =
b11 ;
b11 -
b11 1
b1 /
#820
0!
0*
#830
1!
1*
b11 0
b1 .
b0 ;
b0 /
1(
0'
b0 -
b1 ,
#840
0!
0*
#850
1!
1*
b0 .
b1 =
b11 <
b0 ,
#860
0!
0*
#870
1!
1*
b10 <
#880
0!
0*
#890
1!
1*
b1 <
#900
0!
0*
#910
1!
1*
b0 <
#920
0!
0*
#930
1!
1*
b0 =
b1 ;
b1 -
b0 1
b11 /
#940
0!
0*
#950
1!
1*
b0 0
b11 .
b0 ;
b0 /
1)
0(
0&
1#
b0 -
b11 ,
#960
0!
0*
#970
1!
1*
b0 .
b11 =
b111 <
b0 ,
#980
0!
0*
#990
1!
1*
b110 <
#1000
0!
0*
#1010
1!
1*
b101 <
#1020
0!
0*
#1030
1!
1*
b100 <
#1040
0!
0*
#1050
1!
1*
b11 <
#1060
0!
0*
#1070
1!
1*
b10 <
#1080
0!
0*
#1090
1!
1*
b1 <
#1100
0!
0*
#1110
1!
1*
b0 <
#1120
0!
0*
#1130
1!
1*
b0 =
b11 ;
b11 -
b1 1
b1 /
#1140
0!
0*
#1150
1!
1*
b1 0
b1 .
b0 ;
b0 /
1%
0#
b0 -
b1 ,
#1160
0!
0*
#1170
1!
1*
b0 .
b1 =
b11 <
b0 ,
#1180
0!
0*
#1190
1!
1*
b10 <
#1200
0!
0*
#1210
1!
1*
b1 <
#1220
0!
0*
#1230
1!
1*
b0 <
#1240
0!
0*
#1250
1!
1*
b0 =
b1 ;
b1 -
b100 1
b10 /
