HW1-2/PRJ/HW1_1_RTL.v
`timescale 1ns / 1ns
//8Bit_addsub_carrylookahead
module HW1_1_RTL (
    input [7:0]A,
    input [7:0]B,
    input Add_ctrl,
    output reg [7:0]SUM,
    output reg C_out,
    output Overflow
    );
    always@(A or B or Add_ctrl)
        begin
        if (Add_ctrl == 1)
            {C_out, SUM} = A + B;
        else
            {C_out, SUM} = A - B;
        end
                     
    //check overflow
    assign Overflow = (A[7] & B[7] & Add_ctrl & ~SUM[7]) | (~A[7] & ~B[7] & Add_ctrl & SUM[7]) | 
                  (A[7] & ~B[7] & ~Add_ctrl & ~SUM[7]) | (~A[7] & B[7] & ~Add_ctrl & SUM[7]);       
             
endmodule

HW1-2/PRJ/HW1_1.v
`timescale 1ns / 1ns
//Generate, Propagate, Carry
module CLL (
    output C_out,
    output S3, S2, S1, S0,
    input A3, A2, A1, A0, B3, B2, B1, B0,
    input C0
    );
    wire c1t1,c2t1,c2t2,c3t1,c3t2,c3t3,c4t1,c4t2,c4t3,c4t4;
    wire C1, C2, C3;
    wire [3:0] G, P;
    
    //Carry propagate, Carry generate
    and #(1) (G[0], A0, B0);
    xor #(1) (P[0], A0, B0);
    and #(1) (G[1], A1, B1);
    xor #(1) (P[1], A1, B1);
    and #(1) (G[2], A2, B2);
    xor #(1) (P[2], A2, B2);
    and #(1) (G[3], A3, B3);
    xor #(1) (P[3], A3, B3);
    
    //Carry: Ci = Gi + PiCi
    and #(1) A11 (c1t1, P[0], C0);
    or #(1)  OC1 (C1, G[0], c1t1);
    
    and #(1) A21 (c2t1, P[1], G[0]);
    and #(1) A22 (c2t2, P[1], P[0], C0);
    or #(1)  OC2 (C2, G[1], c2t1, c2t2);
    
    and #(1) A31 (c3t1, P[2], G[1]);
    and #(1) A32 (c3t2, P[2], P[1], G[0]);
    and #(1) A33 (c3t3, P[2], P[1], P[0], C0);
    or #(1)  OC3 (C3, G[2], c3t1, c3t2, c3t3);
    
    and #(1) A41 (c4t1, P[3], G[2]);
    and #(1) A42 (c4t2, P[3], P[2], G[1]);
    and #(1) A43 (c4t3, P[3], P[2], P[1], G[0]);
    and #(1) A44 (c4t4, P[3], P[2], P[1], P[0], C0);
    or #(1)  OC4 (C_out, G[3], c4t1, c4t2, c4t3, c4t4);
    
    //Sum: Si = Pi xor Ci
    xor #(1) (S0, P[0], C0);
    xor #(1) (S1, P[1], C1);
    xor #(1) (S2, P[2], C2);
    xor #(1) (S3, P[3], C3);
        
endmodule


module HW1_1 (
    input [7:0]A,
    input [7:0]B,
    input Add_ctrl,
    output [7:0]SUM,
    output C_out,
    output Overflow
    );
    wire [7:0] B_s;
    wire nAdd_ctrl, C4, C8;
    wire nA7,nB7,nS7,ao1,ao2,ao3,ao4;
    
    //invert Add_ctrl for add=0 sub=1
    not #(1) (nAdd_ctrl, Add_ctrl);
    
    //sub need to + 1
    or #(1) (C0, nAdd_ctrl);
    
    //add or sub
    xor #(1) (B_s[0], nAdd_ctrl, B[0]);
    xor #(1) (B_s[1], nAdd_ctrl, B[1]);
    xor #(1) (B_s[2], nAdd_ctrl, B[2]);
    xor #(1) (B_s[3], nAdd_ctrl, B[3]);
    xor #(1) (B_s[4], nAdd_ctrl, B[4]);
    xor #(1) (B_s[5], nAdd_ctrl, B[5]);
    xor #(1) (B_s[6], nAdd_ctrl, B[6]);
    xor #(1) (B_s[7], nAdd_ctrl, B[7]);
    
    //ALU
    CLL CLL1 (C4, SUM[3], SUM[2], SUM[1], SUM[0], A[3], A[2], A[1], A[0], B_s[3], B_s[2], B_s[1], B_s[0], C0);
    CLL CLL2 (C8, SUM[7], SUM[6], SUM[5], SUM[4], A[7], A[6], A[5], A[4], B_s[7], B_s[6], B_s[5], B_s[4], C4);
    xor #(1) (C_out, C8, nAdd_ctrl);
    
    //check overflow
    not #(1) NA7 (nA7, A[7]);
    not #(1) NB7 (nB7, B[7]);
    not #(1) NS7 (nS7, SUM[7]);
    and #(1) AO1 (ao1, A[7], B[7], Add_ctrl, nS7);
    and #(1) AO2 (ao2, nA7, nB7, Add_ctrl, SUM[7]);
    and #(1) AO3 (ao3, A[7], nB7, nAdd_ctrl, nS7);
    and #(1) AO4 (ao4, nA7, B[7], nAdd_ctrl, SUM[7]);
    or  #(1) OVF (Overflow, ao1, ao2, ao3, ao4);       
endmodule

HW1-1/PRJ/HW1_1_tb.v
`timescale 1ns / 1ns
`include "HW1_1_RTL.v"
`include "HW1_1.v"
module test_HW1_1;
	// Inputs
	reg [7:0]A;
	reg [7:0]B;
	reg Add_ctrl;
	// Outputs
	wire [7:0]SUM;
    wire [7:0]SUM_RTL;
	wire C_out;
    wire C_out_RTL;
    wire Overflow;
    wire Overflow_RTL;
	// Instantiate the Unit Under Test (UUT)
	
    HW1_1 uut (
		.A(A),
		.B(B),
		.Add_ctrl(Add_ctrl),
		.SUM(SUM),
		.C_out(C_out),
        .Overflow(Overflow)
	);
    
    HW1_1_RTL uut2 (
        .A(A),
		.B(B),
		.Add_ctrl(Add_ctrl),
		.SUM(SUM_RTL),
		.C_out(C_out_RTL),
        .Overflow(Overflow_RTL)
    );
    
	initial begin
        //(-6) + (-4)
        A = 8'b11111010;
		B = 8'b11111100;             
        Add_ctrl = 1;
        #20;
        //3 + (-1)
		A = 8'b00000011;
		B = 8'b11111111;
        Add_ctrl = 1;
		#20;
        //79 + 112
        A = 8'b01001111;
		B = 8'b01110000;             
        Add_ctrl = 1;
        #20;
        //(-2) - (-1)
        A = 8'b11111110;
		B = 8'b11111111;             
        Add_ctrl = 0;
        #20;
        //(-128) - 1
        A = 8'b10000000;
		B = 8'b00000001;             
        Add_ctrl = 0;
        #20;
        //64 - (-127)
        A = 8'b01000000;
		B = 8'b10000001;             
        Add_ctrl = 0;
        #20;
		
    $finish;
	end
    
    initial
    $monitor($time, " gate level: A=%b B=%b Add_ctrl=%b SUM=%b Overflow=%b\n\t\t\ \ \ \ \ RTL level: A=%b B=%b Add_ctrl=%b SUM=%b Overflow=%b\n", A,B,Add_ctrl,SUM,Overflow,A,B,Add_ctrl,SUM,Overflow);
    
    initial 
        begin
        $dumpfile("HW1_1_sim.vcd");
        $dumpvars;
        end

endmodule

HW1-1/PRJ/HW1_1_sim.vcd
$date
    Apr  2, 2018  11:20:25
$end
$version
    TOOL:	ncsim	14.10-s005
$end
$timescale
    1 ns
$end

$scope module test_HW1_1 $end
$var reg       8 !    A [7:0] $end
$var reg       8 "    B [7:0] $end
$var reg       1 #    Add_ctrl  $end
$var wire      1 $    SUM [7] $end
$var wire      1 %    SUM [6] $end
$var wire      1 &    SUM [5] $end
$var wire      1 '    SUM [4] $end
$var wire      1 (    SUM [3] $end
$var wire      1 )    SUM [2] $end
$var wire      1 *    SUM [1] $end
$var wire      1 +    SUM [0] $end
$var wire      8 ,    SUM_RTL [7:0] $end
$var wire      1 -    C_out  $end
$var wire      1 .    C_out_RTL  $end
$var wire      1 /    Overflow  $end
$var wire      1 0    Overflow_RTL  $end

$scope module uut $end
$var wire      1 1    A [7] $end
$var wire      1 2    A [6] $end
$var wire      1 3    A [5] $end
$var wire      1 4    A [4] $end
$var wire      1 5    A [3] $end
$var wire      1 6    A [2] $end
$var wire      1 7    A [1] $end
$var wire      1 8    A [0] $end
$var wire      1 9    B [7] $end
$var wire      1 :    B [6] $end
$var wire      1 ;    B [5] $end
$var wire      1 <    B [4] $end
$var wire      1 =    B [3] $end
$var wire      1 >    B [2] $end
$var wire      1 ?    B [1] $end
$var wire      1 @    B [0] $end
$var wire      1 A    Add_ctrl  $end
$var wire      1 $    SUM [7] $end
$var wire      1 %    SUM [6] $end
$var wire      1 &    SUM [5] $end
$var wire      1 '    SUM [4] $end
$var wire      1 (    SUM [3] $end
$var wire      1 )    SUM [2] $end
$var wire      1 *    SUM [1] $end
$var wire      1 +    SUM [0] $end
$var wire      1 -    C_out  $end
$var wire      1 /    Overflow  $end
$var wire      1 B    B_s [7] $end
$var wire      1 C    B_s [6] $end
$var wire      1 D    B_s [5] $end
$var wire      1 E    B_s [4] $end
$var wire      1 F    B_s [3] $end
$var wire      1 G    B_s [2] $end
$var wire      1 H    B_s [1] $end
$var wire      1 I    B_s [0] $end
$var wire      1 J    nAdd_ctrl  $end
$var wire      1 K    C4  $end
$var wire      1 L    C8  $end
$var wire      1 M    nA7  $end
$var wire      1 N    nB7  $end
$var wire      1 O    nS7  $end
$var wire      1 P    ao1  $end
$var wire      1 Q    ao2  $end
$var wire      1 R    ao3  $end
$var wire      1 S    ao4  $end
$var wire      1 T    C0  $end

$scope module CLL1 $end
$var wire      1 K    C_out  $end
$var wire      1 (    S3  $end
$var wire      1 )    S2  $end
$var wire      1 *    S1  $end
$var wire      1 +    S0  $end
$var wire      1 5    A3  $end
$var wire      1 6    A2  $end
$var wire      1 7    A1  $end
$var wire      1 8    A0  $end
$var wire      1 F    B3  $end
$var wire      1 G    B2  $end
$var wire      1 H    B1  $end
$var wire      1 I    B0  $end
$var wire      1 T    C0  $end
$var wire      1 U    c1t1  $end
$var wire      1 V    c2t1  $end
$var wire      1 W    c2t2  $end
$var wire      1 X    c3t1  $end
$var wire      1 Y    c3t2  $end
$var wire      1 Z    c3t3  $end
$var wire      1 [    c4t1  $end
$var wire      1 \    c4t2  $end
$var wire      1 ]    c4t3  $end
$var wire      1 ^    c4t4  $end
$var wire      1 _    C1  $end
$var wire      1 `    C2  $end
$var wire      1 a    C3  $end
$var wire      1 b    G [3] $end
$var wire      1 c    G [2] $end
$var wire      1 d    G [1] $end
$var wire      1 e    G [0] $end
$var wire      1 f    P [3] $end
$var wire      1 g    P [2] $end
$var wire      1 h    P [1] $end
$var wire      1 i    P [0] $end
$upscope $end


$scope module CLL2 $end
$var wire      1 L    C_out  $end
$var wire      1 $    S3  $end
$var wire      1 %    S2  $end
$var wire      1 &    S1  $end
$var wire      1 '    S0  $end
$var wire      1 1    A3  $end
$var wire      1 2    A2  $end
$var wire      1 3    A1  $end
$var wire      1 4    A0  $end
$var wire      1 B    B3  $end
$var wire      1 C    B2  $end
$var wire      1 D    B1  $end
$var wire      1 E    B0  $end
$var wire      1 K    C0  $end
$var wire      1 j    c1t1  $end
$var wire      1 k    c2t1  $end
$var wire      1 l    c2t2  $end
$var wire      1 m    c3t1  $end
$var wire      1 n    c3t2  $end
$var wire      1 o    c3t3  $end
$var wire      1 p    c4t1  $end
$var wire      1 q    c4t2  $end
$var wire      1 r    c4t3  $end
$var wire      1 s    c4t4  $end
$var wire      1 t    C1  $end
$var wire      1 u    C2  $end
$var wire      1 v    C3  $end
$var wire      1 w    G [3] $end
$var wire      1 x    G [2] $end
$var wire      1 y    G [1] $end
$var wire      1 z    G [0] $end
$var wire      1 {    P [3] $end
$var wire      1 |    P [2] $end
$var wire      1 }    P [1] $end
$var wire      1 ~    P [0] $end
$upscope $end

$upscope $end


$scope module uut2 $end
$var wire      8 !!   A [7:0] $end
$var wire      8 "!   B [7:0] $end
$var wire      1 A    Add_ctrl  $end
$var reg       8 #!   SUM [7:0] $end
$var reg       1 $!   C_out  $end
$var wire      1 0    Overflow  $end
$upscope $end

$upscope $end

$enddefinitions $end
$dumpvars
b11111010 !
b11111100 "
1#
x$
x%
x&
x'
x(
x)
x*
x+
b11110110 ,
x-
1.
x/
00
11
12
13
14
15
06
17
08
19
1:
1;
1<
1=
1>
0?
0@
1A
xB
xC
xD
xE
xF
xG
xH
xI
xJ
xK
xL
xM
xN
xO
xP
xQ
xR
xS
xT
xU
xV
xW
xX
xY
xZ
x[
x\
x]
x^
x_
x`
xa
xb
xc
xd
xe
xf
xg
xh
xi
xj
xk
xl
xm
xn
xo
xp
xq
xr
xs
xt
xu
xv
xw
xx
xy
xz
x{
x|
x}
x~
b11111010 !!
b11111100 "!
b11110110 #!
1$!
$end
#1
0e
0c
0M
0N
0J
#2
1B
1C
1D
1E
1F
1G
0H
0I
0T
0R
0S
0Q
0[
0V
0Y
0]
#3
0U
0W
0Z
0^
0i
1h
0d
1g
0f
1b
0~
1z
0}
1y
0|
1x
0{
1w
#4
1L
0p
1v
0m
0q
1u
0k
0n
0r
1t
0j
0l
0o
0s
1K
0`
0X
0\
0+
0_
#5
1*
0a
1)
1'
1&
1%
1$
1-
#6
0O
0(
#7
0P
#8
0/
#20
b11 !
b11111111 "
b11111111 "!
1?
1@
b11 !!
01
02
03
04
05
18
b10 #!
b10 ,
#21
1i
1f
0b
1~
0z
1}
0y
1|
0x
1M
1{
0w
1I
1H
#22
0h
1d
0i
1e
0L
0$
1s
0v
0%
1o
0u
0&
1l
0t
0'
1j
0K
1(
#23
1'
0j
0l
0o
0s
1&
1%
1$
0-
1_
1`
1X
1\
#24
1K
1a
0)
#25
0(
0'
1j
1l
1o
1s
#26
1L
1v
1u
1t
#27
0&
0%
0$
1-
#28
1O
#40
b1001111 !
b1110000 "
b1110000 "!
09
0=
0>
0?
0@
b1001111 !!
12
15
16
b10111111 #!
0$!
10
0.
b10111111 ,
#41
0g
1c
0f
1b
0|
1x
0I
0H
0G
0F
1N
0B
#42
0{
1f
0b
1g
0c
1h
0d
1i
0e
1%
0o
0s
#43
0\
0X
0L
0_
1+
0`
1$
#44
0O
1Q
1)
0-
0a
0K
#45
1'
0j
0l
1(
1/
#46
0u
0t
#47
1&
0%
#60
b11111110 !
b11111111 "
0#
0A
b11111111 "!
19
1=
1>
1?
1@
b11111110 !!
11
13
14
08
b11111111 #!
1$!
1.
b11111111 ,
00
#61
0i
0~
1z
0}
1y
0M
1{
1I
1H
1G
1F
0N
1B
1J
0Q
#62
0/
0B
0C
0D
0E
0F
0G
0H
0I
1-
1T
0$
1p
1u
0&
1t
0'
#63
1&
1%
1L
1O
1~
0z
1}
0y
1|
0x
#64
0v
0p
0%
0u
0&
0t
1'
0-
#65
1&
1%
0L
1$
#66
0O
1-
#80
b10000000 !
b1 "
b1 "!
09
0:
0;
0<
0=
0>
0?
b10000000 !!
02
03
04
05
06
07
b1111111 #!
0$!
10
0.
b1111111 ,
#81
0h
0g
0f
0~
0}
0|
1H
1G
1F
1E
1D
1C
1N
1B
#82
0{
1w
1|
1}
1~
1f
1g
1h
#83
1L
0$
#84
1O
0-
#85
1R
#86
1/
#100
b1000000 !
b10000001 "
b10000001 "!
19
b1000000 !!
01
12
b10111111 #!
1$!
1.
b10111111 ,
#101
0|
1x
1M
1{
0R
0w
0N
0B
#102
0{
0L
0/
1v
0%
#103
1$
1-
#104
0O
1S
#105
1/
